pyslingshot/__init__.py
pyslingshot/lineage.py
pyslingshot/plotter.py
pyslingshot/slingshot.py
pyslingshot/util.py
pyslingshot-0.2.0.dist-info/METADATA
pyslingshot-0.2.0.dist-info/WHEEL
pyslingshot-0.2.0.dist-info/RECORD
